difw/__init__.py
difw/cpab.py
difw/backend/__init__.py
difw/backend/numpy/__init__.py
difw/backend/numpy/functions.py
difw/backend/numpy/interpolation.py
difw/backend/numpy/transformer.py
difw/backend/pytorch/__init__.py
difw/backend/pytorch/functions.py
difw/backend/pytorch/interpolation.py
difw/backend/pytorch/transformer.cpp
difw/backend/pytorch/transformer.py
difw/backend/pytorch/transformer_cuda.cpp
difw/backend/pytorch/transformer_cuda.cu
difw/backend/pytorch/transformer_slow.py
difw/core/__init__.py
difw/core/cpab_ops.cpp
difw/core/cpab_ops.cu
difw/core/cpab_ops.cuh
difw/core/cpab_ops.h
difw/core/tessellation.py
difw/core/utility.py
difw-0.0.31.dist-info/LICENSE
difw-0.0.31.dist-info/METADATA
difw-0.0.31.dist-info/WHEEL
difw-0.0.31.dist-info/top_level.txt
difw-0.0.31.dist-info/RECORD
