Metadata-Version: 2.1
Name: difw
Version: 0.0.31
Summary: Compute one dimensional CPAB transformations in Numpy and Pytorch
Home-page: https://github.com/imartinezl/difw
Author: Iñigo Martinez
Author-email: inigomlap@gmail.com
Maintainer: Iñigo Martinez
Maintainer-email: inigomlap@gmail.com
License: MIT license
Project-URL: Bug Reports, https://github.com/imartinezl/difw/issues
Project-URL: Documentation, https://difw.readthedocs.io
Project-URL: Source Code, https://github.com/imartinezl/difw
Keywords: diffeomorphisms,tessellations,transformations,continuous piecewise-affine,velocity fields
Classifier: Development Status :: 3 - Alpha
Classifier: Intended Audience :: Developers
Classifier: License :: OSI Approved :: MIT License
Classifier: Natural Language :: English
Classifier: Environment :: GPU :: NVIDIA CUDA
Classifier: Programming Language :: C++
Classifier: Programming Language :: Python :: 3
Classifier: Programming Language :: Python :: 3.5
Classifier: Programming Language :: Python :: 3.6
Classifier: Programming Language :: Python :: 3.7
Classifier: Programming Language :: Python :: 3.8
Classifier: Programming Language :: Python :: 3.9
Requires-Python: <4,>=3.6
License-File: LICENSE
Requires-Dist: numpy (>=1.20)
Requires-Dist: matplotlib (>=3.4.0)
Requires-Dist: torch (>=1.8.0)
Requires-Dist: scipy
Requires-Dist: ninja
